modsqual.py
modsqual-0.5.1.dist-info/DESCRIPTION.rst
modsqual-0.5.1.dist-info/METADATA
modsqual-0.5.1.dist-info/RECORD
modsqual-0.5.1.dist-info/WHEEL
modsqual-0.5.1.dist-info/metadata.json
modsqual-0.5.1.dist-info/top_level.txt
