Metadata-Version: 2.0
Name: modsqual
Version: 0.5.1
Summary: An lxml wrapper for working with MODS XML data.
Home-page: https://github.com/saverkamp/modsqual
Author: Shawn Averkamp
Author-email: shawnaverkamp@gmail.com
License: MIT
Platform: UNKNOWN
Classifier: Programming Language :: Python :: 2.7
Requires-Dist: xmltodict
